qwikswitchapi/__about__.py
qwikswitchapi/__init__.py
qwikswitchapi/client.py
qwikswitchapi/constants.py
qwikswitchapi/entities.py
qwikswitchapi/exceptions.py
qwikswitchapi/utility.py
qwikswitch_api-0.0.10.dist-info/METADATA
qwikswitch_api-0.0.10.dist-info/WHEEL
qwikswitch_api-0.0.10.dist-info/licenses/LICENSE
qwikswitch_api-0.0.10.dist-info/RECORD
