Metadata-Version: 2.4
Name: qwikswitch_api
Version: 0.0.10
Summary: A Python wrapper around the QwikSwitch API
Author-email: Riaan Hanekom <riaan@hanekom.io>
License-File: LICENSE
Classifier: License :: OSI Approved :: MIT License
Classifier: Operating System :: OS Independent
Classifier: Programming Language :: Python :: 3
Requires-Python: >=3.8
Requires-Dist: requests
Provides-Extra: dev
Requires-Dist: build; extra == 'dev'
Requires-Dist: packagename[docs,tests]; extra == 'dev'
Requires-Dist: twine; extra == 'dev'
Provides-Extra: docs
Requires-Dist: pydata-sphinx-theme; extra == 'docs'
Requires-Dist: sphinx; extra == 'docs'
Provides-Extra: tests
Requires-Dist: pytest; extra == 'tests'
Requires-Dist: pytest-cov; extra == 'tests'
Requires-Dist: pytest-flakes; extra == 'tests'
Requires-Dist: requests-mock; extra == 'tests'
